{"per_page":10,"total":4,"current":1,"data":[{"year":"2019","months":[{"month":"7","entries":[{"title":"Nodejs中的异步编程 -- Promise","date":"2019-07-25T06:33:46.000Z","slug":"nodejs-promise"},{"title":"Nodejs中的异步编程 -- Async模块","date":"2019-07-25T02:44:09.000Z","slug":"nodejs-aysnc"},{"title":"（一）基本概念 —— Java多线程学习","date":"2019-07-24T06:13:30.000Z","slug":"thread4j-intro"},{"title":"undefined","date":"2019-07-21T22:54:14.000Z","slug":"other-story01"},{"title":"你们的笑能治愈整个世界","date":"2019-07-19T09:15:41.000Z","slug":"other-skit01"},{"title":"生命游戏教程","date":"2019-07-17T12:00:27.000Z","slug":"other-gameoflife"},{"title":"子进程以及通信-NodeJS","date":"2019-07-17T01:07:46.000Z","slug":"nodejs-child-process"},{"title":"NodeJS中的网络操作","date":"2019-07-17T00:49:31.000Z","slug":"nodejs-nodetcp"},{"title":"图简单实现以及深度优先搜索和广度优先搜索","date":"2019-07-07T09:01:19.000Z","slug":"algorithm-graph"},{"title":"事件发射器-NodeJS","date":"2019-07-01T21:44:12.000Z","slug":"nodejs-eventemitter"}]}]}]}